dddttt.py
setup.py
dddttt.egg-info/PKG-INFO
dddttt.egg-info/SOURCES.txt
dddttt.egg-info/dependency_links.txt
dddttt.egg-info/not-zip-safe
dddttt.egg-info/top_level.txt